pyoti/__init__.py
pyoti/classes.py
pyoti/exceptions.py
pyoti/utils.py
pyoti/domains/__init__.py
pyoti/domains/checkdmarc.py
pyoti/domains/circlpdns.py
pyoti/domains/irisinvestigate.py
pyoti/domains/whoisxml.py
pyoti/emails/__init__.py
pyoti/emails/disposableemails.py
pyoti/emails/emailrepio.py
pyoti/hashes/__init__.py
pyoti/hashes/circlhashlookup.py
pyoti/hashes/malwarebazaar.py
pyoti/hashes/malwarehashregistry.py
pyoti/ips/__init__.py
pyoti/ips/abuseipdb.py
pyoti/ips/greynoise.py
pyoti/ips/spamhausintel.py
pyoti/multis/__init__.py
pyoti/multis/circlpssl.py
pyoti/multis/dnsblocklist.py
pyoti/multis/hybridanalysis.py
pyoti/multis/maltiverseioc.py
pyoti/multis/misp.py
pyoti/multis/onyphe.py
pyoti/multis/otx.py
pyoti/multis/pulsedive.py
pyoti/multis/threatfox.py
pyoti/multis/urlhaus.py
pyoti/multis/urlscan.py
pyoti/multis/virustotal.py
pyoti/multis/xforce.py
pyoti/urls/__init__.py
pyoti/urls/googlesafebrowsing.py
pyoti/urls/linkpreview.py
pyoti/urls/phishtank.py
pyoti/urls/proofpointurldecoder.py
pyoti-0.3.3.2.dist-info/LICENSE
pyoti-0.3.3.2.dist-info/METADATA
pyoti-0.3.3.2.dist-info/WHEEL
pyoti-0.3.3.2.dist-info/top_level.txt
pyoti-0.3.3.2.dist-info/RECORD
