Metadata-Version: 2.1
Name: pyoti
Version: 0.3.3.2
Summary: Python API for Threat Intelligence
Home-page: https://github.com/RH-ISAC/PyOTI
Author: goodlandsecurity
Author-email: jj.josing@rhisac.org
License: GNU GPLv3
Project-URL: Bug Tracker, https://github.com/RH-ISAC/PyOTI/issues
Project-URL: Changelog, https://github.com/RH-ISAC/PyOTI/blob/master/CHANGELOG.md
Platform: any
Classifier: Development Status :: 5 - Production/Stable
Classifier: Environment :: Console
Classifier: License :: OSI Approved :: GNU General Public License v3 (GPLv3)
Classifier: Programming Language :: Python :: 3.7
Classifier: Programming Language :: Python :: 3.8
Classifier: Programming Language :: Python :: 3.9
Classifier: Intended Audience :: Information Technology
Classifier: Topic :: Security
Classifier: Topic :: Utilities
Requires-Python: >=3.7
License-File: LICENSE
Requires-Dist: requests
Requires-Dist: aiodns
Requires-Dist: disposable-email-domains
Provides-Extra: jupyter_notebook
Requires-Dist: jupyterlab ; extra == 'jupyter_notebook'
Requires-Dist: notebook ; extra == 'jupyter_notebook'
